COPYING
MANIFEST.in
README.rst
bootstrap.py
buildout.cfg
setup.py
docs/conf.py
docs/index.rst
xbob/__init__.py
xbob.db.verification.filelist.egg-info/PKG-INFO
xbob.db.verification.filelist.egg-info/SOURCES.txt
xbob.db.verification.filelist.egg-info/dependency_links.txt
xbob.db.verification.filelist.egg-info/entry_points.txt
xbob.db.verification.filelist.egg-info/namespace_packages.txt
xbob.db.verification.filelist.egg-info/not-zip-safe
xbob.db.verification.filelist.egg-info/requires.txt
xbob.db.verification.filelist.egg-info/top_level.txt
xbob/db/__init__.py
xbob/db/verification/__init__.py
xbob/db/verification/filelist/__init__.py
xbob/db/verification/filelist/driver.py
xbob/db/verification/filelist/models.py
xbob/db/verification/filelist/query.py
xbob/db/verification/filelist/test.py
xbob/db/verification/filelist/example_fl/dev/for_models.lst
xbob/db/verification/filelist/example_fl/dev/for_probes.lst
xbob/db/verification/filelist/example_fl/dev/for_scores.lst
xbob/db/verification/filelist/example_fl/dev/for_tnorm.lst
xbob/db/verification/filelist/example_fl/dev/for_znorm.lst
xbob/db/verification/filelist/example_fl/eval/for_models.lst
xbob/db/verification/filelist/example_fl/eval/for_probes.lst
xbob/db/verification/filelist/example_fl/eval/for_scores.lst
xbob/db/verification/filelist/example_fl/eval/for_tnorm.lst
xbob/db/verification/filelist/example_fl/eval/for_znorm.lst
xbob/db/verification/filelist/example_fl/norm/train_optional_world_1.lst
xbob/db/verification/filelist/example_fl/norm/train_optional_world_2.lst
xbob/db/verification/filelist/example_fl/norm/train_world.lst